LICENSE
MANIFEST.in
README.rst
setup.cfg
setup.py
versioneer.py
tpDcc/__init__.py
tpDcc/tools/__init__.py
tpDcc/tools/scripteditor/__init__.py
tpDcc/tools/scripteditor/__logging__.ini
tpDcc/tools/scripteditor/__version__.py
tpDcc/tools/scripteditor/_version.py
tpDcc/tools/scripteditor/core/__init__.py
tpDcc/tools/scripteditor/core/client.py
tpDcc/tools/scripteditor/core/consts.py
tpDcc/tools/scripteditor/core/controller.py
tpDcc/tools/scripteditor/core/model.py
tpDcc/tools/scripteditor/core/session.py
tpDcc/tools/scripteditor/core/tool.py
tpDcc/tools/scripteditor/core/toolset.py
tpDcc/tools/scripteditor/core/view.py
tpDcc/tools/scripteditor/dccs/__init__.py
tpDcc/tools/scripteditor/dccs/maya/__init__.py
tpDcc/tools/scripteditor/dccs/maya/server.py
tpDcc/tools/scripteditor/resources/styles/completer.css
tpDcc/tools/scripteditor/syntax/__init__.py
tpDcc/tools/scripteditor/syntax/python.py
tpDcc/tools/scripteditor/widgets/__init__.py
tpDcc/tools/scripteditor/widgets/completers.py
tpDcc/tools/scripteditor/widgets/console.py
tpDcc/tools/scripteditor/widgets/script.py
tpDcc_tools_scripteditor.egg-info/PKG-INFO
tpDcc_tools_scripteditor.egg-info/SOURCES.txt
tpDcc_tools_scripteditor.egg-info/dependency_links.txt
tpDcc_tools_scripteditor.egg-info/not-zip-safe
tpDcc_tools_scripteditor.egg-info/requires.txt
tpDcc_tools_scripteditor.egg-info/top_level.txt