Metadata-Version: 2.1
Name: tpDcc-tools-scripteditor
Version: 0.0.1
Summary: Tool to edit scripts.
Home-page: https://github.com/tpDcc/tpDcc-tools-scripteditor
Author: Tomas Poveda
Author-email: tpovedatd@gmail.com
License: MIT
Platform: UNKNOWN
Provides-Extra: dev
Provides-Extra: test
